marstuff/__init__.py
marstuff/bases.py
marstuff/client.py
marstuff/objects/camera.py
marstuff/objects/manifest.py
marstuff/objects/photo.py
marstuff/objects/rover.py
marstuff/utils.py
marstuff-0.2.0.dist-info/LICENSE
marstuff-0.2.0.dist-info/WHEEL
marstuff-0.2.0.dist-info/METADATA
marstuff-0.2.0.dist-info/RECORD
