Metadata-Version: 2.1
Name: marstuff
Version: 0.2.0
Summary: A Python Wrapper for NASA's Mars Rover Photos API
Home-page: https://github.com/ajratnam/marstuff
License: MIT
Keywords: nasa,api,mars,rover
Author: Ajay Ratnam
Author-email: ajratnam.dev@gmail.com
Maintainer: Ajay Ratnam
Maintainer-email: ajratnam.dev@gmail.com
Requires-Python: >=3.9,<4.0
Classifier: Development Status :: 1 - Planning
Classifier: Intended Audience :: Developers
Classifier: License :: OSI Approved
Classifier: License :: OSI Approved :: MIT License
Classifier: Natural Language :: English
Classifier: Programming Language :: Python
Classifier: Programming Language :: Python :: 3
Classifier: Programming Language :: Python :: 3.9
Classifier: Programming Language :: Python :: 3.10
Classifier: Programming Language :: Python :: 3.9
Classifier: Topic :: Scientific/Engineering
Classifier: Topic :: Scientific/Engineering :: Astronomy
Classifier: Topic :: Software Development
Classifier: Topic :: Software Development :: Libraries
Classifier: Topic :: Software Development :: Libraries :: Python Modules
Classifier: Topic :: Software Development :: Version Control
Classifier: Topic :: Software Development :: Version Control :: Git
Classifier: Topic :: Utilities
Requires-Dist: Pillow (>=8.3.2,<9.0.0)
Requires-Dist: httpx[http2] (>=0.19.0,<0.20.0)
Project-URL: Documentation, https://github.com/ajratnam/marstuff
Project-URL: Repository, https://github.com/ajratnam/marstuff
